fufpy/__init__.py
fufpy/_version.py
fufpy/dynamic_partition.py
fufpy/test.py
fufpy-0.1.1.dist-info/LICENSE
fufpy-0.1.1.dist-info/METADATA
fufpy-0.1.1.dist-info/WHEEL
fufpy-0.1.1.dist-info/top_level.txt
fufpy-0.1.1.dist-info/RECORD
