Metadata-Version: 2.2
Name: fufpy
Version: 0.1.1
Summary: Fast union-find in Python
Author-email: Luis Scoccola <luis.scoccola@gmail.com>
Maintainer-email: Luis Scoccola <luis.scoccola@gmail.com>
Requires-Python: >=3.10
License-File: LICENSE
Requires-Dist: numpy
Requires-Dist: numba
